{
  "display_name": "Bustamante",
  "fetched_at_utc": "2025-04-01T01:24:35+00:00",
  "migration_source": "map-of-ini/data/Bustamante.json",
  "publication_count": 29,
  "publications": [
    {
      "author_pub_id": "RH_0tmMAAAAJ:hqOjcs7Dif8C",
      "citation": "Telecommunications Policy Research Conference, 2019",
      "num_citations": 1,
      "pub_url": "",
      "pub_year": "2019",
      "title": "A Collaborative Enforcement Mechanism for Spectrum Sharing Using Blockchain and Smart Contracts: An application for the 1695-1710MHz band"
    },
    {
      "author_pub_id": "RH_0tmMAAAAJ:UebtZRa9Y70C",
      "citation": "IEEE Communications Magazine 61 (2), 58-63, 2022",
      "num_citations": 4,
      "pub_url": "",
      "pub_year": "2022",
      "title": "A techno-economic study of spectrum sharing with blockchain and smart contracts"
    },
    {
      "author_pub_id": "RH_0tmMAAAAJ:eQOLeE2rZwMC",
      "citation": "TPRC, 2018",
      "num_citations": 1,
      "pub_url": "",
      "pub_year": "2018",
      "title": "Agent-Based Modeling Approach for Developing Enforcement Mechanisms in Spectrum Sharing Scenarios: An Application for the 1695-1710mhz Band"
    },
    {
      "author_pub_id": "RH_0tmMAAAAJ:WF5omc3nYNoC",
      "citation": "",
      "num_citations": 4,
      "pub_url": "",
      "pub_year": "2018",
      "title": "Agent-based modelling approach for developing enforcement mechanisms in spectrum sharing scenarios: An application for the 1695-1710mhz band"
    },
    {
      "author_pub_id": "RH_0tmMAAAAJ:u-x6o8ySG0sC",
      "citation": "University of Pittsburgh, 2017",
      "num_citations": 5,
      "pub_url": "",
      "pub_year": "2017",
      "title": "Analysis of experimental licenses of the federal communications commission (fcc)"
    },
    {
      "author_pub_id": "RH_0tmMAAAAJ:Y0pCki6q_DkC",
      "citation": "IEEE International Symposium on Dynamic Spectrum Access Networks, 2017",
      "num_citations": 1,
      "pub_url": "",
      "pub_year": "2017",
      "title": "Analysis of the Experimental Licenses of the Federal Communication Commission"
    },
    {
      "author_pub_id": "RH_0tmMAAAAJ:ufrVoPGSRksC",
      "citation": "University of Pittsburgh, 2021",
      "num_citations": 0,
      "pub_url": "",
      "pub_year": "2021",
      "title": "Analyzing Usage Conflict Situations in Localized Spectrum Sharing Scenarios: An Agent-Based Modeling and Machine Learning Approach"
    },
    {
      "author_pub_id": "RH_0tmMAAAAJ:Tyk-4Ss8FVUC",
      "citation": "ICN... the... International Conference on Networks, 2019",
      "num_citations": 7,
      "pub_url": "",
      "pub_year": "2019",
      "title": "Crowdsourced misuse detection in dynamic spectrum sharing wireless networks"
    },
    {
      "author_pub_id": "RH_0tmMAAAAJ:3fE2CSJIrl8C",
      "citation": "Telecommunications Policy 47 (10), 102667, 2023",
      "num_citations": 3,
      "pub_url": "",
      "pub_year": "2023",
      "title": "Examining the US amateur-radio community through a polycentricity lens"
    },
    {
      "author_pub_id": "RH_0tmMAAAAJ:roLk4NBRz8UC",
      "citation": "",
      "num_citations": 2,
      "pub_url": "",
      "pub_year": "2017",
      "title": "Exploration of the Federal Communications Commission’s Experimental Radio Service (ERS): Understanding ten years of experimental spectrum licenses"
    },
    {
      "author_pub_id": "RH_0tmMAAAAJ:IjCSPb-OGe4C",
      "citation": "Data & Policy 2, e6, 2020",
      "num_citations": 7,
      "pub_url": "",
      "pub_year": "2020",
      "title": "Federal Communications Commission’s experimental radio service as a vehicle for dynamic spectrum access: An analysis of 10 years of experimental licenses data"
    },
    {
      "author_pub_id": "RH_0tmMAAAAJ:YsMSGLbcyi4C",
      "citation": "Blockchain applications to public sector governance. Blockchain applications …, 2022",
      "num_citations": 0,
      "pub_url": "",
      "pub_year": "2022",
      "title": "Government by Code"
    },
    {
      "author_pub_id": "RH_0tmMAAAAJ:qjMakFHDy7sC",
      "citation": "Frontiers in blockchain 5, 869665, 2022",
      "num_citations": 32,
      "pub_url": "",
      "pub_year": "2022",
      "title": "Government by code? Blockchain applications to public sector governance"
    },
    {
      "author_pub_id": "RH_0tmMAAAAJ:UeHWp8X0CEIC",
      "citation": "TPRC47: The 47th Research Conference on Communication, Information and …, 2019",
      "num_citations": 12,
      "pub_url": "",
      "pub_year": "2019",
      "title": "Is Blockchain the Next Step in the Evolution Chain of [Market] Intermediaries?"
    },
    {
      "author_pub_id": "RH_0tmMAAAAJ:8k81kl-MbHgC",
      "citation": "",
      "num_citations": 0,
      "pub_url": "",
      "pub_year": "2020",
      "title": "JOURNAL OF INSTITUTIONAL ECONOMICS"
    },
    {
      "author_pub_id": "RH_0tmMAAAAJ:W7OEmFMy1HYC",
      "citation": "Telecommunications Policy Research Conference, 2019",
      "num_citations": 1,
      "pub_url": "",
      "pub_year": "2019",
      "title": "Market Disputes| Legal, Social, and Long-Term Implications for an Evolving Spectrum Market"
    },
    {
      "author_pub_id": "RH_0tmMAAAAJ:_FxGoFyzp5QC",
      "citation": "GLOBECOM 2020-2020 IEEE Global Communications Conference, 1-6, 2020",
      "num_citations": 3,
      "pub_url": "",
      "pub_year": "2020",
      "title": "Matchmaking of volunteers and channels for dynamic spectrum access enforcement"
    },
    {
      "author_pub_id": "RH_0tmMAAAAJ:u5HHmVD_uO8C",
      "citation": "International Journal on Advances in Networks and Services Volume 12, Number …, 2019",
      "num_citations": 5,
      "pub_url": "",
      "pub_year": "2019",
      "title": "Misuse detection in dynamic spectrum sharing wireless networks across multiple channels"
    },
    {
      "author_pub_id": "RH_0tmMAAAAJ:2osOgNQ5qMEC",
      "citation": "Available at SSRN 4189545, 2022",
      "num_citations": 0,
      "pub_url": "",
      "pub_year": "2022",
      "title": "Mitigating conflict situations in spectrum sharing: A localized and decentralized governance approach"
    },
    {
      "author_pub_id": "RH_0tmMAAAAJ:5nxA0vEk-isC",
      "citation": "SSRN Electronic Journal, 2023",
      "num_citations": 2,
      "pub_url": "",
      "pub_year": "2023",
      "title": "On the governance of federated platforms"
    },
    {
      "author_pub_id": "RH_0tmMAAAAJ:Se3iqnhoufwC",
      "citation": "Cosmos+ Taxis 10 (3), 4, 2019",
      "num_citations": 17,
      "pub_url": "",
      "pub_year": "2019",
      "title": "Ostrom amongst the machines: Blockchain as a knowledge commons"
    },
    {
      "author_pub_id": "RH_0tmMAAAAJ:zYLM7Y9cAGgC",
      "citation": "SSRN Electronic Journal, 2022",
      "num_citations": 4,
      "pub_url": "",
      "pub_year": "2022",
      "title": "Polycentric Governance in the US Amateur-Radio Community: Unassigned Spectrum and Promoting Open Innovation"
    },
    {
      "author_pub_id": "RH_0tmMAAAAJ:kNdYIx-mwKoC",
      "citation": "",
      "num_citations": 0,
      "pub_url": "",
      "title": "Scholarship@ PITT LAW"
    },
    {
      "author_pub_id": "RH_0tmMAAAAJ:9yKSN-GCB0IC",
      "citation": "Journal of Institutional Economics 16 (6), 863-882, 2020",
      "num_citations": 22,
      "pub_url": "",
      "pub_year": "2020",
      "title": "Spectrum anarchy: why self-governance of the radio spectrum works better than we think"
    },
    {
      "author_pub_id": "RH_0tmMAAAAJ:d1gkVwhDpl0C",
      "citation": "2020 IEEE 17th Annual Consumer Communications & Networking Conference (CCNC …, 2020",
      "num_citations": 5,
      "pub_url": "",
      "pub_year": "2020",
      "title": "Spectrum misuse detection in cooperative wireless networks"
    },
    {
      "author_pub_id": "RH_0tmMAAAAJ:KlAtU1dfN6UC",
      "citation": "Journal of Information Policy 14, 2024",
      "num_citations": 1,
      "pub_url": "",
      "pub_year": "2024",
      "title": "Spectrum Rights in Outer Space: Interference Management for Low Earth Orbit (LEO) Broadband Constellations"
    },
    {
      "author_pub_id": "RH_0tmMAAAAJ:LkGwnXOMwfcC",
      "citation": "SSRN Electronic Journal, 2022",
      "num_citations": 5,
      "pub_url": "",
      "pub_year": "2022",
      "title": "Spectrum Rights in Outer Space: Interference Management for Mega-Constellations"
    },
    {
      "author_pub_id": "RH_0tmMAAAAJ:0EnyYjriUFMC",
      "citation": "TPRC48: The 48th Research Conference on Communication, Information and …, 2020",
      "num_citations": 3,
      "pub_url": "",
      "pub_year": "2020",
      "title": "Toward automated enforcement of radio interference"
    },
    {
      "author_pub_id": "RH_0tmMAAAAJ:MXK_kJrjxJIC",
      "citation": "SSRN Electronic Journal, 2023",
      "num_citations": 2,
      "pub_url": "",
      "pub_year": "2023",
      "title": "Unassigned Spectrum: An Institutional Analysis of Radio Spectrum Management"
    }
  ],
  "schema_version": 1,
  "scholar_id": "RH_0tmMAAAAJ"
}
