{
  "display_name": "Mohan",
  "fetched_at_utc": "2025-04-01T01:25:26+00:00",
  "migration_source": "map-of-iii/data/Mohan.json",
  "publication_count": 13,
  "publications": [
    {
      "author_pub_id": "w3_2J7EAAAAJ:Tyk-4Ss8FVUC",
      "citation": "Computers & operations research 14 (3), 183-196, 1987",
      "num_citations": 4,
      "pub_url": "",
      "pub_year": "1987",
      "title": "A network approach to cohort personnel planning using cross-sectional data"
    },
    {
      "author_pub_id": "w3_2J7EAAAAJ:9yKSN-GCB0IC",
      "citation": "US Patent 7,156,305, 2007",
      "num_citations": 33,
      "pub_url": "",
      "pub_year": "2007",
      "title": "Apparatus and method for authenticating products"
    },
    {
      "author_pub_id": "w3_2J7EAAAAJ:u5HHmVD_uO8C",
      "citation": "US Patent 7,850,081, 2010",
      "num_citations": 41,
      "pub_url": "",
      "pub_year": "2010",
      "title": "Apparatus and method for authenticating products"
    },
    {
      "author_pub_id": "w3_2J7EAAAAJ:Y0pCki6q_DkC",
      "citation": "Demystifying AI for the Enterprise, 193-222, 2021",
      "num_citations": 2,
      "pub_url": "",
      "pub_year": "2021",
      "title": "Artificial intelligence in retail"
    },
    {
      "author_pub_id": "w3_2J7EAAAAJ:IjCSPb-OGe4C",
      "citation": "US Patent 7,174,230, 2007",
      "num_citations": 93,
      "pub_url": "",
      "pub_year": "2007",
      "title": "Computer integrated manufacturing techniques"
    },
    {
      "author_pub_id": "w3_2J7EAAAAJ:u-x6o8ySG0sC",
      "citation": "US Patent 7,069,101, 2006",
      "num_citations": 83,
      "pub_url": "",
      "pub_year": "2006",
      "title": "Computer integrated manufacturing techniques"
    },
    {
      "author_pub_id": "w3_2J7EAAAAJ:d1gkVwhDpl0C",
      "citation": "Journal of Software Maintenance: Research and Practice 8 (4), 269-280, 1996",
      "num_citations": 3,
      "pub_url": "",
      "pub_year": "1996",
      "title": "Evolutionary Method of Delivery as Applied to a Large Re‐engineering Effort"
    },
    {
      "author_pub_id": "w3_2J7EAAAAJ:qjMakFHDy7sC",
      "citation": "European Journal of Operational Research 161 (1), 86-110, 2005",
      "num_citations": 18,
      "pub_url": "",
      "pub_year": "2005",
      "title": "Executing production schedules in the face of uncertainties: a review and some future directions"
    },
    {
      "author_pub_id": "w3_2J7EAAAAJ:W7OEmFMy1HYC",
      "citation": "",
      "num_citations": 2,
      "pub_url": "",
      "pub_year": "2022",
      "title": "Leadership Lessons with The Beatles - Actionable Tips and Tools for Becoming Better at Leading"
    },
    {
      "author_pub_id": "w3_2J7EAAAAJ:UeHWp8X0CEIC",
      "citation": "US Patent App. 11/442,691, 2006",
      "num_citations": 22,
      "pub_url": "",
      "pub_year": "2006",
      "title": "Method, apparatus, system and computer readable medium for certifying and securing custody in product supply chains"
    },
    {
      "author_pub_id": "w3_2J7EAAAAJ:YsMSGLbcyi4C",
      "citation": "",
      "num_citations": 0,
      "pub_url": "",
      "pub_year": "2018",
      "title": "Roots and Wings: Inspiring Stories of Indian Women in Engineering"
    },
    {
      "author_pub_id": "w3_2J7EAAAAJ:zYLM7Y9cAGgC",
      "citation": "US Patent 8,464,947, 2013",
      "num_citations": 10,
      "pub_url": "",
      "pub_year": "2013",
      "title": "System and method for authenticating products"
    },
    {
      "author_pub_id": "w3_2J7EAAAAJ:2osOgNQ5qMEC",
      "citation": "Carnegie Mellon University, Tepper School of Business, 1992",
      "num_citations": 0,
      "pub_url": "",
      "pub_year": "1992",
      "title": "The Semi-Linear Programming Algorithm: A Solution Technique for Production Smoothing Problems"
    }
  ],
  "schema_version": 1,
  "scholar_id": "w3_2J7EAAAAJ"
}
